switchbot_api/__init__.py
switchbot_api/commands.py
switchbot_api/exceptions.py
switchbot_api/models.py
switchbot_api/utils.py
switchbot_api-2.10.0.dist-info/METADATA
switchbot_api-2.10.0.dist-info/WHEEL
switchbot_api-2.10.0.dist-info/licenses/LICENSE
switchbot_api-2.10.0.dist-info/RECORD
