Metadata-Version: 2.4
Name: switchbot_api
Version: 2.10.0
Summary: An asynchronous library to use Switchbot API
License: MIT
License-File: LICENSE
Author: Ravaka Razafimanantsoa
Author-email: contact@ravaka.dev
Requires-Python: >=3.10,<4.0
Classifier: License :: OSI Approved :: MIT License
Classifier: Programming Language :: Python :: 3
Classifier: Programming Language :: Python :: 3.10
Classifier: Programming Language :: Python :: 3.11
Classifier: Programming Language :: Python :: 3.12
Classifier: Programming Language :: Python :: 3.13
Classifier: Programming Language :: Python :: 3.14
Requires-Dist: aiohttp (>=3.0.0)
Project-URL: Repository, https://github.com/SeraphicCorp/py-switchbot-api
